LICENSE.md
MANIFEST.in
README.md
setup.py
libs/__init__.py
libs/pdtest.py
libs/proxy.py
pad/__init__.py
pad/interpreter.py
pad/lexer.py
pad/libloader.py
pad/ltypes.py
pad/parse.py
pad/walker.py
padlang.egg-info/PKG-INFO
padlang.egg-info/SOURCES.txt
padlang.egg-info/dependency_links.txt
padlang.egg-info/entry_points.txt
padlang.egg-info/requires.txt
padlang.egg-info/top_level.txt
samples/classes.pad
samples/code.pad
samples/gui.pad
samples/http.pad
samples/sample.py
tests/test_interpreter.py