Metadata-Version: 1.1
Name: padlang
Version: 1.0.21
Summary: PADLang is yet another interpreted language now with focus on Pascal/C-like syntax
Home-page: https://github.com/zaklaus/padlang
Author: Dominik Madarasz
Author-email: zaklaus@madaraszd.net
License: Apache 2.0
Keywords: interpreted development language pascal c
Platform: UNKNOWN
Classifier: Development Status :: 3 - Alpha
Classifier: Intended Audience :: Developers
Classifier: Programming Language :: Other
Classifier: License :: OSI Approved :: Apache Software License
Classifier: Programming Language :: Python :: 3.3
Classifier: Programming Language :: Python :: 3.4
Classifier: Programming Language :: Python :: 3.5
